pptb/__init__.py
pptb/nn/__init__.py
pptb/nn/functional.py
pptb/nn/layer.py
pptb/nn/loss.py
pptb/optimizer/__init__.py
pptb/optimizer/lr.py
pptb/tools/__init__.py
pptb/tools/mixing.py
pptb/vision/__init__.py
pptb/vision/models/__init__.py
pptb/vision/models/convmixer.py
pptb-0.2.0.dist-info/LICENSE
pptb-0.2.0.dist-info/WHEEL
pptb-0.2.0.dist-info/METADATA
pptb-0.2.0.dist-info/RECORD
